pytcx/__init__.py
pytcx/py.typed
pytcx-0.3.2.dist-info/AUTHORS.rst
pytcx-0.3.2.dist-info/LICENSE
pytcx-0.3.2.dist-info/METADATA
pytcx-0.3.2.dist-info/WHEEL
pytcx-0.3.2.dist-info/RECORD
