Metadata-Version: 2.1
Name: pytcx
Version: 0.3.2
Summary: GPX parsing for Python
Home-page: https://github.com/heoga/pytcx
License: MIT
Keywords: tcx
Author: Karl Odie
Author-email: karlodie@gmail.com
Requires-Python: >=3.9,<4.0
Classifier: Development Status :: 2 - Pre-Alpha
Classifier: Intended Audience :: Developers
Classifier: License :: OSI Approved :: MIT License
Classifier: Natural Language :: English
Classifier: Programming Language :: Python :: 3
Classifier: Programming Language :: Python :: 3.9
Classifier: Programming Language :: Python :: 3.10
Classifier: Programming Language :: Python :: 3.11
Classifier: Programming Language :: Python :: 3.12
Requires-Dist: defusedxml (>=0.7.1,<0.8.0)
Project-URL: Repository, https://github.com/heoga/pytcx
